babeldjango/__init__.py
babeldjango/extract.py
babeldjango/middleware.py
babeldjango/templatetags/__init__.py
babeldjango/templatetags/babel.py
BabelDjango_onefinestay-0.2.4.dist-info/DESCRIPTION.rst
BabelDjango_onefinestay-0.2.4.dist-info/entry_points.txt
BabelDjango_onefinestay-0.2.4.dist-info/METADATA
BabelDjango_onefinestay-0.2.4.dist-info/metadata.json
BabelDjango_onefinestay-0.2.4.dist-info/RECORD
BabelDjango_onefinestay-0.2.4.dist-info/top_level.txt
BabelDjango_onefinestay-0.2.4.dist-info/WHEEL
