Metadata-Version: 2.0
Name: BabelDjango-onefinestay
Version: 0.2.4
Summary: Utilities for using Babel in Django
Home-page: http://babel.edgewall.org/wiki/BabelDjango
Author: Edgewall Software
Author-email: python-babel@googlegroups.com
License: BSD
Platform: UNKNOWN
Requires-Dist: Babel
